{ "height":15,
 "layers":[
        {
         "data":[0, 0, 0, 0, 0, 0, 0, 0, 0, 0, 0, 0, 0, 0, 0, 0, 0, 17, 0, 17, 0, 18, 17, 0, 17, 20, 0, 0, 17, 0, 17, 0, 0, 17, 0, 17, 0, 18, 17, 0, 17, 20, 0, 0, 17, 0, 17, 0, 0, 17, 0, 17, 0, 18, 17, 0, 17, 20, 0, 0, 17, 0, 17, 0, 0, 17, 0, 17, 0, 18, 17, 42, 17, 20, 0, 0, 17, 0, 17, 0, 0, 17, 0, 17, 0, 0, 0, 0, 0, 0, 0, 0, 17, 0, 17, 0, 0, 0, 0, 0, 0, 18, 20, 0, 18, 20, 0, 0, 0, 0, 0, 0, 19, 0, 17, 17, 0, 0, 0, 0, 0, 0, 0, 0, 17, 17, 0, 19, 46, 0, 0, 0, 0, 18, 17, 19, 17, 20, 0, 0, 0, 0, 0, 46, 0, 0, 0, 0, 0, 18, 17, 17, 17, 20, 0, 0, 0, 0, 0, 0, 0, 17, 0, 17, 0, 18, 17, 0, 17, 20, 0, 0, 17, 0, 17, 0, 0, 17, 0, 17, 0, 18, 17, 0, 17, 20, 0, 0, 17, 0, 17, 0, 0, 17, 0, 17, 0, 0, 0, 0, 0, 0, 0, 0, 17, 0, 17, 0, 0, 17, 0, 17, 0, 0, 18, 17, 20, 0, 0, 0, 17, 0, 17, 0, 0, 0, 0, 0, 0, 0, 18, 70, 20, 0, 0, 0, 0, 0, 0, 0],
         "height":15,
         "name":"Ground",
         "opacity":1,
         "type":"tilelayer",
         "visible":true,
         "width":16,
         "x":0,
         "y":0
        }],
 "nextobjectid":1,
 "orientation":"orthogonal",
 "renderorder":"right-down",
 "tiledversion":"1.0.3",
 "tileheight":16,
 "tilesets":[
        {
         "columns":25,
         "firstgid":1,
         "image":"battlecity_general.png",
         "imageheight":256,
         "imagewidth":400,
         "margin":0,
         "name":"battlecity",
         "spacing":0,
         "tilecount":400,
         "tileheight":16,
         "tilewidth":16
        }],
 "tilewidth":16,
 "type":"map",
 "version":1,
 "width":16
}